{
 "tournament": "OPEN_CHAMPIONSHIP_2026",
 "updatedUtc": "2026-07-18T11:48:16Z",
 "cvMaePct": 2.519,
 "date": "2026-07-14 00:00:00",
 "predicted": {
  "Scottie Scheffler": 24.14,
  "Rory McIlroy": 10.4,
  "Tommy Fleetwood": 19.27,
  "Matt Fitzpatrick": 32.28,
  "Xander Schauffele": 13.76,
  "Jon Rahm": 6.32,
  "Ludvig Aberg": 9.45,
  "Justin Rose": 10.44,
  "Cameron Young": 8.5,
  "Tyrrell Hatton": 14.32,
  "Collin Morikawa": 12.76,
  "Chris Gotterup": 19.09,
  "Bryson DeChambeau": 4.29,
  "Viktor Hovland": 33.1,
  "Wyndham Clark": 18.02,
  "Robert MacIntyre": 24.51,
  "Shane Lowry": 9.29,
  "Sam Burns": 19.56,
  "Russell Henley": 8.01,
  "Brooks Koepka": 5.31,
  "Justin Thomas": 10.67,
  "Alex Fitzpatrick": 15.32,
  "Joaquin Niemann": 19.61,
  "Jordan Spieth": 5.82,
  "Aaron Rai": 11.04,
  "Patrick Reed": 9.97,
  "Patrick Cantlay": 5.67,
  "Hideki Matsuyama": 6.27,
  "Si Woo Kim": 15.7,
  "Min Woo Lee": 14.34,
  "Ben Griffin": 8.9,
  "Tom Kim": 17.54,
  "Corey Conners": 5.53,
  "Cameron Smith": 2.31,
  "Maverick McNealy": 3.37,
  "J.J. Spaun": 8.56,
  "Eugenio Lopez-Chacarra": 5.15,
  "Marco Penge": 2.16,
  "Harris English": 2.35,
  "Jake Knapp": 1.17,
  "Akshay Bhatia": 8.96,
  "Brian Harman": 5.58,
  "Nicolai Hojgaard": 5.32,
  "Sepp Straka": 0.81,
  "Keegan Bradley": 5.66,
  "Kurt Kitayama": 7.03,
  "Rickie Fowler": 7.79,
  "Kristoffer Reitan": 1.8,
  "David Puig": 1.23,
  "Adam Scott": 2.18,
  "Victor Perez": 6.03,
  "Max Homa": 3.47,
  "Jacob Bridgeman": 2.62,
  "Ryan Gerard": 2.16,
  "Jason Day": 1.34,
  "Alex Noren": 0.82,
  "Rasmus Hojgaard": 1.32,
  "Matt Wallace": 2.17,
  "Gary Woodland": 1.42,
  "Ryan Fox": 2.85,
  "Harry Hall": 0.7,
  "Sahith Theegala": 2.41,
  "Rasmus Neergaard-Petersen": 0.81,
  "Angel Ayora Fanegas": 0.84,
  "Sungjae Im": 1.02,
  "Daniel Berger": 0.88,
  "Jayden Trey Schaper": 0.69,
  "Hao-Tong Li": 0.76,
  "Aldrich Potgieter": 0.89,
  "Jordan L. Smith": 1.25,
  "Keith Mitchell": 3.11,
  "Ryo Hisatsune": 3.49,
  "J.T. Poston": 0.67,
  "Michael Thorbjornsen": 3.01,
  "Lucas Herbert": 0.99,
  "Thomas Detry": 1.03,
  "Tom McKibbin": 1.68,
  "John Keefer": 3.83,
  "Casey Jarvis": 0.67,
  "Eric Cole": 0.62,
  "Bud Cauley": 0.94,
  "Max Greyserman": 0.72,
  "Alex Smalley": 0.38,
  "Michael Brennan": 0.55,
  "Nick Taylor": 0.85,
  "Andrew Novak": 0.45,
  "Pierceson Coody": 0.97,
  "Daniel Hillier": 0.15,
  "Michael Kim": 0.57,
  "Bernd Wiesberger": 0.33,
  "John Parry": 0.69,
  "Scott Vincent": 0.54,
  "Billy Horschel": 0.64,
  "Frederic Lacroix": 0.3,
  "Jackson Suber": 2.09,
  "Sam Stevens": 0.44,
  "Sami Valimaki": 0.32,
  "Matthew Jordan": 0.38,
  "Jesper Svensson": 0.64,
  "Hennie Du Plessis": 0.87,
  "Matthew McCarty": 0.22,
  "Laurie Canter": 0.49,
  "Daniel Brown": 0.38,
  "Josele Ballester": 0.21,
  "Francesco Molinari": 0.29,
  "Joe Dean": 0.32,
  "Francesco Laporta": 0.14,
  "Peter Uihlein": 0.21,
  "Nicolas Echavarria": 0.97,
  "Stewart Cink": 0.9,
  "Padraig Harrington": 0.28,
  "Andy Sullivan": 0.28,
  "Antoine Rozner": 0.18,
  "Shaun Norris": 0.31,
  "Alistair Docherty": 0.23,
  "Keita Nakajima": 1.68,
  "Kota Kaneko": 0.18,
  "Dan Bradbury": 0.08,
  "Martin Couvra": 0.05,
  "MJ Daffue": 0.25,
  "Caleb Surratt": 0.03,
  "Kazuma Kobori": 0.22,
  "Adrien Saddier": 0.28,
  "Joakim Lagergren": 0.07,
  "Michael Hollick": 1.13,
  "Matthew Southgate": 0.07,
  "Jeongwoo Ham": 0.19,
  "Naoyuki Kataoka": 0.18,
  "Jack Buchanan": 0.06,
  "James Nicholas": 0.0,
  "Henrik Stenson": 0.29,
  "Sam Bairstow": 0.07,
  "Kazuki Higa": 0.4,
  "Ren Yonezawa": 0.19,
  "Tim Wiedemeyer": 0.08,
  "Travis Smyth": 0.07,
  "Matthew Baldwin": 0.01,
  "Cameron John": 0.06,
  "Stuart Grehan": 0.05,
  "Austen Truslow": 0.05,
  "Ryutaro Nagano": 0.15,
  "Lev Grinberg": 0.05,
  "Jack McDonald": 0.04,
  "Mason Howell": 0.06,
  "Darren Clarke": 0.5,
  "Tiger Christensen": 0.23,
  "Marcus Plunkett": 0.04,
  "Jiho Yang": 0.08,
  "Mateo Pulcini": 0.02,
  "Baard Bjoernevik Skogen": 0.27,
  "David Duval": 0.16,
  "Thomas Sloman": 0.06,
  "Fifa Laopakdee": 0.05,
  "Alejandro De Castro Piera": 0.05,
  "Nevill Ruiter": 0.05,
  "David Howard": 0.04
 }
}