{
 "tournament": "US_OPEN_2026",
 "actual": {
  "Scottie Scheffler": 16.66,
  "Rory McIlroy": 16.55,
  "Jon Rahm": 13.21,
  "Bryson DeChambeau": 2.71,
  "Cameron Young": 17.81,
  "Xander Schauffele": 23.86,
  "Tommy Fleetwood": 31.95,
  "Brooks Koepka": 5.72,
  "Ludvig Aberg": 18.17,
  "Matt Fitzpatrick": 42.33,
  "Tyrrell Hatton": 15.08,
  "Collin Morikawa": 10.8,
  "Justin Rose": 7.58,
  "Justin Thomas": 7.84,
  "Chris Gotterup": 23.18,
  "Viktor Hovland": 7.95,
  "Russell Henley": 22.15,
  "Patrick Reed": 32.34,
  "Wyndham Clark": 13.49,
  "Sam Burns": 21.02,
  "Hideki Matsuyama": 11.1,
  "J.J. Spaun": 9.8,
  "Joaquin Niemann": 4.75,
  "Patrick Cantlay": 15.54,
  "Si Woo Kim": 26.2,
  "Shane Lowry": 10.64,
  "Jordan Spieth": 5.45,
  "Sepp Straka": 2.35,
  "Ben Griffin": 3.1,
  "Robert MacIntyre": 6.22,
  "Kristoffer Reitan": 4.18,
  "Min Woo Lee": 4.86,
  "Cameron Smith": 9.87,
  "Maverick McNealy": 9.85,
  "Alex Smalley": 2.73,
  "Aaron Rai": 4.95,
  "Jake Knapp": 4.39,
  "Bud Cauley": 1.94,
  "Harris English": 9.48,
  "Rickie Fowler": 2.11,
  "Nicolai Hojgaard": 1.88,
  "Jason Day": 1.5,
  "Ryan Gerard": 4.83,
  "Adam Scott": 10.78,
  "Alex Fitzpatrick": 8.2,
  "Gary Woodland": 3.67,
  "Akshay Bhatia": 1.64,
  "Kurt Kitayama": 7.73,
  "Jacob Bridgeman": 3.66,
  "Corey Conners": 1.44,
  "Daniel Berger": 1.16,
  "David Puig": 1.85,
  "Keegan Bradley": 1.59,
  "Alex Noren": 3.12,
  "Sahith Theegala": 3.1,
  "Sungjae Im": 1.04,
  "Carlos Ortiz": 0.26,
  "Ryan Fox": 3.0,
  "Nick Taylor": 1.05,
  "Dustin Johnson": 2.0,
  "Lucas Herbert": 0.39,
  "Jackson Koivun": 2.45,
  "Tom Kim": 2.39,
  "Davis Thompson": 0.16,
  "Harry Hall": 0.97,
  "Brian Harman": 2.5,
  "Keith Mitchell": 1.62,
  "Sam Stevens": 0.44,
  "Michael Kim": 0.34,
  "Sudarshan Yellamaraju": 1.72,
  "John Keefer": 0.24,
  "Ryo Hisatsune": 3.01,
  "Andrew Novak": 0.24,
  "Max Greyserman": 0.45,
  "Jayden Trey Schaper": 0.48,
  "Michael Brennan": 0.21,
  "Pierceson Coody": 0.22,
  "Matthew McCarty": 0.36,
  "Chris Kirk": 0.38,
  "Matti Schmid": 0.12,
  "Nicolas Echavarria": 0.24,
  "Billy Horschel": 0.7,
  "Andrew Putnam": 1.24,
  "Patrick Rodgers": 0.57,
  "Matthew Jordan": 0.17,
  "Caleb Surratt": 0.29,
  "Emiliano Grillo": 0.6,
  "Max McGreevy": 0.12,
  "Nathan Kimsey": 0.05,
  "Zac Blair": 0.07,
  "John Parry": 0.15,
  "Laurie Canter": 0.07,
  "Peter Uihlein": 0.16,
  "Niklas Norgaard Moller": 0.0,
  "Benjamin James": 0.29,
  "Ben Kohles": 0.82,
  "Kevin Roy": 0.17,
  "Adrien Dumont De Chassart": 0.21,
  "Graeme McDowell": 0.25,
  "Ugo Coussaud": 0.01,
  "Jackson Suber": 2.82,
  "William Mouw": 0.22,
  "Ben Silverman": 0.07,
  "Cole Hammer": 0.07,
  "Chandler Phillips": 0.06,
  "Jimmy Stanger": 0.48,
  "Nick Hardy": 0.01,
  "Padraig Harrington": 0.6,
  "Taylor Montgomery": 0.07,
  "Miles Russell": 0.24,
  "Rocco Repetto Taylor": 0.01,
  "Adrien Saddier": 0.02,
  "Alejandro Tosti": 0.07,
  "James Nicholas": 0.12,
  "Harry Higgs": 0.04,
  "Carl Yuan": 0.0,
  "Taihei Sato": 0.01,
  "Angel Hidalgo": 0.04,
  "Filippo Celli": 0.01,
  "Brandon Wu": 0.11,
  "Ethan Fang": 0.04,
  "Jackson Herrington": 0.01,
  "Preston Stout": 0.06,
  "T.K. Kim": 0.03,
  "Jackson Van Paris": 0.03,
  "Robbie Higgins": 0.0,
  "Cooper Dossey": 0.75,
  "Ryder Cowan": 0.03,
  "Eric Lee": 0.0,
  "Chase Kyes": 0.0,
  "Hamilton Coleman": 0.0,
  "Mason Howell": 0.05,
  "Kaito Onishi": 0.07,
  "Marcelo Rozo": 0.02,
  "Marek Fleming": 0.0,
  "Vaughn Harber": 0.01,
  "Manav Shah": 0.0,
  "Brandon Holtz": 0.01,
  "Jake Sollon": 0.02,
  "Ryuichi Oiwa": 0.01,
  "Jake Peacock": 0.09,
  "Arni Sveinsson": 0.03,
  "Logan Reilly": 0.01,
  "Jackson Ormond": 0.02,
  "Mateo Pulcini": 0.01,
  "Matthew Robles": 0.0,
  "J.B. Holmes": 0.09,
  "Greyson Leach": 0.0,
  "Giuseppe Puebla": 0.0,
  "Yohann Benson": 0.0
 },
 "actualFpts": {
  "Scottie Scheffler": 75.0,
  "Rory McIlroy": 60.5,
  "Jon Rahm": 20.0,
  "Bryson DeChambeau": 24.5,
  "Cameron Young": 43.0,
  "Xander Schauffele": 60.5,
  "Tommy Fleetwood": 62.0,
  "Brooks Koepka": 15.0,
  "Ludvig Aberg": 51.5,
  "Matt Fitzpatrick": 51.0,
  "Tyrrell Hatton": 69.5,
  "Collin Morikawa": 57.5,
  "Justin Rose": 61.5,
  "Justin Thomas": 61.5,
  "Chris Gotterup": 45.0,
  "Viktor Hovland": 21.0,
  "Russell Henley": 39.5,
  "Patrick Reed": 22.5,
  "Wyndham Clark": 102.0,
  "Sam Burns": 77.0,
  "Hideki Matsuyama": 33.0,
  "J.J. Spaun": 19.0,
  "Joaquin Niemann": 79.0,
  "Patrick Cantlay": 20.5,
  "Si Woo Kim": 25.0,
  "Shane Lowry": 19.0,
  "Jordan Spieth": 37.5,
  "Sepp Straka": 22.5,
  "Ben Griffin": 53.0,
  "Robert MacIntyre": 53.0,
  "Kristoffer Reitan": 18.5,
  "Min Woo Lee": 20.0,
  "Cameron Smith": 21.0,
  "Maverick McNealy": 47.5,
  "Alex Smalley": 17.0,
  "Aaron Rai": 56.5,
  "Jake Knapp": 16.5,
  "Bud Cauley": 36.5,
  "Harris English": 16.5,
  "Rickie Fowler": 21.0,
  "Nicolai Hojgaard": 11.0,
  "Jason Day": -2.0,
  "Ryan Gerard": 17.5,
  "Adam Scott": 16.5,
  "Alex Fitzpatrick": 50.5,
  "Gary Woodland": 67.5,
  "Akshay Bhatia": 51.5,
  "Kurt Kitayama": 42.0,
  "Jacob Bridgeman": 48.5,
  "Corey Conners": 51.5,
  "Daniel Berger": 17.0,
  "David Puig": 15.5,
  "Keegan Bradley": 42.5,
  "Alex Noren": 18.0,
  "Sahith Theegala": 57.0,
  "Sungjae Im": 47.0,
  "Carlos Ortiz": 20.0,
  "Ryan Fox": 52.0,
  "Nick Taylor": 18.0,
  "Dustin Johnson": 64.0,
  "Lucas Herbert": 26.5,
  "Jackson Koivun": 57.0,
  "Tom Kim": 79.5,
  "Davis Thompson": 15.0,
  "Harry Hall": 11.5,
  "Brian Harman": 47.5,
  "Keith Mitchell": 80.5,
  "Sam Stevens": 65.0,
  "Michael Kim": 41.5,
  "Sudarshan Yellamaraju": 17.5,
  "John Keefer": 49.5,
  "Ryo Hisatsune": 45.0,
  "Andrew Novak": 23.0,
  "Max Greyserman": 51.5,
  "Jayden Trey Schaper": 15.5,
  "Michael Brennan": 45.5,
  "Pierceson Coody": 54.0,
  "Matthew McCarty": 12.0,
  "Chris Kirk": 13.0,
  "Matti Schmid": 14.0,
  "Nicolas Echavarria": 42.0,
  "Billy Horschel": 25.0,
  "Andrew Putnam": 37.5,
  "Patrick Rodgers": 32.0,
  "Matthew Jordan": 19.5,
  "Caleb Surratt": 43.0,
  "Emiliano Grillo": 58.0,
  "Max McGreevy": 51.5,
  "Nathan Kimsey": 16.5,
  "Zac Blair": 44.5,
  "John Parry": 54.5,
  "Laurie Canter": 41.0,
  "Peter Uihlein": 41.5,
  "Benjamin James": 51.0,
  "Ben Kohles": 54.5,
  "Kevin Roy": 15.5,
  "Adrien Dumont De Chassart": 56.0,
  "Graeme McDowell": 11.5,
  "Ugo Coussaud": 15.5,
  "Jackson Suber": 23.5,
  "William Mouw": 36.5,
  "Ben Silverman": 16.0,
  "Cole Hammer": 16.5,
  "Chandler Phillips": 15.0,
  "Jimmy Stanger": 19.0,
  "Nick Hardy": 15.0,
  "Padraig Harrington": 9.0,
  "Taylor Montgomery": 15.0,
  "Miles Russell": 41.5,
  "Rocco Repetto Taylor": 6.0,
  "Adrien Saddier": 15.0,
  "Alejandro Tosti": 16.0,
  "James Nicholas": 39.5,
  "Harry Higgs": 50.0,
  "Taihei Sato": 13.5,
  "Angel Hidalgo": 45.5,
  "Filippo Celli": 21.0,
  "Brandon Wu": 19.0,
  "Ethan Fang": 12.0,
  "Jackson Herrington": 13.5,
  "Preston Stout": 24.0,
  "T.K. Kim": 5.5,
  "Jackson Van Paris": 37.5,
  "Cooper Dossey": 11.5,
  "Ryder Cowan": 50.5,
  "Mason Howell": 19.0,
  "Kaito Onishi": 21.5,
  "Marcelo Rozo": 16.0,
  "Vaughn Harber": 18.0,
  "Brandon Holtz": 16.0,
  "Jake Sollon": 10.5,
  "Ryuichi Oiwa": 21.0,
  "Jake Peacock": 11.5,
  "Arni Sveinsson": 4.5,
  "Logan Reilly": 17.0,
  "Jackson Ormond": 10.0,
  "Mateo Pulcini": 14.0,
  "J.B. Holmes": 17.5
 },
 "updatedUtc": "2026-06-25T15:52:16Z",
 "date": "2026-06-18 00:00:00",
 "colab": {
  "Scottie Scheffler": 23.74,
  "Rory McIlroy": 25.89,
  "Jon Rahm": 16.49,
  "Bryson DeChambeau": 8.21,
  "Cameron Young": 11.9,
  "Xander Schauffele": 17.77,
  "Tommy Fleetwood": 24.31,
  "Brooks Koepka": 8.39,
  "Ludvig Aberg": 11.25,
  "Matt Fitzpatrick": 12.82,
  "Tyrrell Hatton": 13.16,
  "Collin Morikawa": 8.96,
  "Justin Rose": 5.96,
  "Justin Thomas": 8.02,
  "Chris Gotterup": 11.55,
  "Viktor Hovland": 14.22,
  "Russell Henley": 17.7,
  "Patrick Reed": 12.31,
  "Wyndham Clark": 13.06,
  "Sam Burns": 23.15,
  "Hideki Matsuyama": 9.09,
  "J.J. Spaun": 14.24,
  "Joaquin Niemann": 7.76,
  "Patrick Cantlay": 12.53,
  "Si Woo Kim": 18.66,
  "Shane Lowry": 10.15,
  "Jordan Spieth": 6.92,
  "Sepp Straka": 3.41,
  "Ben Griffin": 9.46,
  "Robert MacIntyre": 5.13,
  "Kristoffer Reitan": 9.73,
  "Min Woo Lee": 6.24,
  "Cameron Smith": 8.4,
  "Maverick McNealy": 13.02,
  "Alex Smalley": 3.98,
  "Aaron Rai": 9.48,
  "Jake Knapp": 3.88,
  "Bud Cauley": 12.27,
  "Harris English": 11.54,
  "Rickie Fowler": 2.97,
  "Nicolai Hojgaard": 1.77,
  "Jason Day": 1.9,
  "Ryan Gerard": 10.03,
  "Adam Scott": 10.3,
  "Alex Fitzpatrick": 12.49,
  "Gary Woodland": 2.42,
  "Akshay Bhatia": 1.96,
  "Kurt Kitayama": 11.91,
  "Jacob Bridgeman": 4.58,
  "Corey Conners": 1.63,
  "Daniel Berger": 1.77,
  "David Puig": 5.09,
  "Keegan Bradley": 4.89,
  "Alex Noren": 2.43,
  "Sahith Theegala": 2.35,
  "Sungjae Im": 1.17,
  "Carlos Ortiz": 1.26,
  "Ryan Fox": 6.75,
  "Nick Taylor": 1.38,
  "Dustin Johnson": 2.6,
  "Lucas Herbert": 1.89,
  "Jackson Koivun": 1.71,
  "Tom Kim": 2.69,
  "Davis Thompson": 1.22,
  "Harry Hall": 1.01,
  "Brian Harman": 1.67,
  "Keith Mitchell": 3.23,
  "Sam Stevens": 1.22,
  "Michael Kim": 2.13,
  "Sudarshan Yellamaraju": 1.15,
  "John Keefer": 1.52,
  "Ryo Hisatsune": 0.44,
  "Andrew Novak": 1.29,
  "Max Greyserman": 1.49,
  "Jayden Trey Schaper": 1.53,
  "Michael Brennan": 0.67,
  "Pierceson Coody": 0.45,
  "Matthew McCarty": 0.38,
  "Chris Kirk": 0.51,
  "Matti Schmid": 0.87,
  "Nicolas Echavarria": 0.99,
  "Billy Horschel": 0.51,
  "Andrew Putnam": 0.54,
  "Patrick Rodgers": 0.39,
  "Matthew Jordan": 0.07,
  "Caleb Surratt": 0.13,
  "Emiliano Grillo": 0.79,
  "Max McGreevy": 0.43,
  "Nathan Kimsey": 0.48,
  "Zac Blair": 0.14,
  "John Parry": 0.11,
  "Laurie Canter": 0.16,
  "Peter Uihlein": 0.05,
  "Niklas Norgaard Moller": 0.86,
  "Benjamin James": 0.3,
  "Ben Kohles": 0.42,
  "Kevin Roy": 0.1,
  "Adrien Dumont De Chassart": 0.06,
  "Graeme McDowell": 0.09,
  "Ugo Coussaud": 0.43,
  "Jackson Suber": 3.96,
  "William Mouw": 0.33,
  "Ben Silverman": 0.28,
  "Cole Hammer": 0.06,
  "Chandler Phillips": 0.3,
  "Jimmy Stanger": 0.1,
  "Nick Hardy": 0.07,
  "Padraig Harrington": 0.37,
  "Taylor Montgomery": 0.0,
  "Miles Russell": 0.12,
  "Rocco Repetto Taylor": 0.32,
  "Adrien Saddier": 0.26,
  "Alejandro Tosti": 0.06,
  "James Nicholas": 0.01,
  "Harry Higgs": 0.01,
  "Carl Yuan": 0.03,
  "Taihei Sato": 0.08,
  "Angel Hidalgo": 0.08,
  "Filippo Celli": 0.17,
  "Brandon Wu": 0.07,
  "Ethan Fang": 0.1,
  "Jackson Herrington": 0.07,
  "Preston Stout": 0.33,
  "T.K. Kim": 0.32,
  "Jackson Van Paris": 0.0,
  "Robbie Higgins": 0.0,
  "Cooper Dossey": 0.39,
  "Ryder Cowan": 0.1,
  "Eric Lee": 0.1,
  "Chase Kyes": 0.06,
  "Hamilton Coleman": 0.07,
  "Mason Howell": 0.04,
  "Kaito Onishi": 0.01,
  "Marcelo Rozo": 0.0,
  "Marek Fleming": 0.06,
  "Vaughn Harber": 0.06,
  "Manav Shah": 0.06,
  "Brandon Holtz": 0.06,
  "Jake Sollon": 0.07,
  "Ryuichi Oiwa": 0.01,
  "Jake Peacock": 0.02,
  "Arni Sveinsson": 0.07,
  "Logan Reilly": 0.06,
  "Jackson Ormond": 0.06,
  "Mateo Pulcini": 0.06,
  "Matthew Robles": 0.06,
  "J.B. Holmes": 0.06,
  "Greyson Leach": 0.06,
  "Giuseppe Puebla": 0.21,
  "Yohann Benson": 0.21
 },
 "colabMaePct": 1.714
}